easy_mvp/__init__.py
easy_mvp/abstract_presenter.py
easy_mvp/application_manager.py
easy_mvp/exception.py
easy_mvp/intent.py
easy_mvp/window.py
easy_mvp-0.2.0.dist-info/LICENSE
easy_mvp-0.2.0.dist-info/METADATA
easy_mvp-0.2.0.dist-info/WHEEL
easy_mvp-0.2.0.dist-info/top_level.txt
easy_mvp-0.2.0.dist-info/RECORD
