Metadata-Version: 2.1
Name: easy-mvp
Version: 0.2.0
Summary: Construct MVP PyQt5 application easily
Home-page: https://github.com/R0land013/easy-mvp
Author: Rolando Rio Garaboa
Author-email: rolandorio06@gmail.com
Classifier: Programming Language :: Python :: 3
Classifier: License :: OSI Approved :: MIT License
Classifier: Operating System :: OS Independent
License-File: LICENSE
Requires-Dist: PyQt5 (>=5.15.6)
